messages_local/MessagesLocal.py
messages_local/__init__.py
messages_local/main.py
messages_local-0.0.103.dist-info/METADATA
messages_local-0.0.103.dist-info/WHEEL
messages_local-0.0.103.dist-info/top_level.txt
messages_local-0.0.103.dist-info/RECORD
