Metadata-Version: 2.4
Name: messages-local
Version: 0.0.103
Home-page: https://github.com/circles-zone/messages-local-python-package
Author: Circles
Author-email: info@circlez.ai
Classifier: Programming Language :: Python :: 3
Classifier: Operating System :: OS Independent
Requires-Dist: item-local>=0.0.9
Requires-Dist: queue-worker-local>=0.0.37
Requires-Dist: label-message-local>=0.0.4
Requires-Dist: message-local>=0.0.150
Requires-Dist: whatsapp-message-vonage-local>=0.0.19
Requires-Dist: whataspp-message-inforu-local>=0.0.12
Requires-Dist: sms-message-aws-sns-local>=0.0.35
Requires-Dist: email-message-aws-ses-local>=0.0.13
Requires-Dist: facebook-message-selenium-local
Dynamic: author
Dynamic: author-email
Dynamic: classifier
Dynamic: description
Dynamic: description-content-type
Dynamic: home-page
Dynamic: requires-dist
